design.plone.contenttypes-6.3.11-py3.11-nspkg.pth
design/plone/contenttypes/__init__.py
design/plone/contenttypes/configure.zcml
design/plone/contenttypes/overrides.zcml
design/plone/contenttypes/permissions.zcml
design/plone/contenttypes/schema_overrides.py
design/plone/contenttypes/setuphandlers.py
design/plone/contenttypes/testing.py
design/plone/contenttypes/utils.py
design/plone/contenttypes/adapters/__init__.py
design/plone/contenttypes/adapters/configure.zcml
design/plone/contenttypes/adapters/interfaces.py
design/plone/contenttypes/adapters/query.py
design/plone/contenttypes/adapters/searchabletext_indexers.py
design/plone/contenttypes/adapters/servizi_correlati.py
design/plone/contenttypes/behaviors/__init__.py
design/plone/contenttypes/behaviors/additional_help_infos.py
design/plone/contenttypes/behaviors/address.py
design/plone/contenttypes/behaviors/argomenti.py
design/plone/contenttypes/behaviors/configure.zcml
design/plone/contenttypes/behaviors/contatti.py
design/plone/contenttypes/behaviors/dataset_correlati.py
design/plone/contenttypes/behaviors/descrizione_estesa.py
design/plone/contenttypes/behaviors/evento.py
design/plone/contenttypes/behaviors/exclude_from_search.py
design/plone/contenttypes/behaviors/geolocation.py
design/plone/contenttypes/behaviors/info_testata.py
design/plone/contenttypes/behaviors/luoghi_correlati.py
design/plone/contenttypes/behaviors/luogo.py
design/plone/contenttypes/behaviors/multi_file.py
design/plone/contenttypes/behaviors/news_additional_fields.py
design/plone/contenttypes/behaviors/servizi_correlati.py
design/plone/contenttypes/behaviors/show_modified.py
design/plone/contenttypes/behaviors/strutture_correlate.py
design/plone/contenttypes/behaviors/trasparenza.py
design/plone/contenttypes/behaviors/update_note.py
design/plone/contenttypes/browser/__init__.py
design/plone/contenttypes/browser/bando.py
design/plone/contenttypes/browser/configure.zcml
design/plone/contenttypes/browser/trasparenza.py
design_plone_contenttypes-6.3.11.dist-info/licenses/LICENSE.GPL
design_plone_contenttypes-6.3.11.dist-info/licenses/LICENSE.rst
design_plone_contenttypes-6.3.11.dist-info/METADATA
design_plone_contenttypes-6.3.11.dist-info/WHEEL
design_plone_contenttypes-6.3.11.dist-info/entry_points.txt
design_plone_contenttypes-6.3.11.dist-info/namespace_packages.txt
design_plone_contenttypes-6.3.11.dist-info/top_level.txt
design_plone_contenttypes-6.3.11.dist-info/RECORD
