Metadata-Version: 2.4
Name: design.plone.contenttypes
Version: 6.3.11
Summary: DesignItalia contenty types
Home-page: https://github.com/collective/design.plone.contenttypes
Author: RedTurtle
Author-email: sviluppoplone@redturtle.it
License: GPL version 2
Project-URL: PyPI, https://pypi.python.org/pypi/design.plone.contenttypes
Project-URL: Source, https://github.com/RedTurtle/design.plone.contenttypes
Project-URL: Tracker, https://github.com/RedTurtle/design.plone.contenttypes/issues
Keywords: Python Plone
Classifier: Development Status :: 5 - Production/Stable
Classifier: Environment :: Web Environment
Classifier: Framework :: Plone
Classifier: Framework :: Plone :: Addon
Classifier: Framework :: Plone :: 6.0
Classifier: Programming Language :: Python
Classifier: Programming Language :: Python :: 3.8
Classifier: Programming Language :: Python :: 3.9
Classifier: Programming Language :: Python :: 3.10
Classifier: Programming Language :: Python :: 3.11
Classifier: Operating System :: OS Independent
Classifier: License :: OSI Approved :: GNU General Public License v2 (GPLv2)
Requires-Python: >=3.8
License-File: LICENSE.GPL
License-File: LICENSE.rst
Requires-Dist: setuptools
Requires-Dist: z3c.jbot
Requires-Dist: plone.api>=1.8.4
Requires-Dist: plone.app.dexterity>2.6.9
Requires-Dist: collective.venue[geolocation]
Requires-Dist: collective.volto.blocksfield>=2.2.0
Requires-Dist: collective.z3cform.datagridfield
Requires-Dist: plone.formwidget.geolocation
Requires-Dist: redturtle.volto>=5.5.3
Requires-Dist: redturtle.bandi>=1.5.0
Requires-Dist: z3c.unconfigure
Requires-Dist: plone.restapi
Requires-Dist: collective.taxonomy>=3.1
Requires-Dist: openpyxl
Requires-Dist: collective.volto.enhancedlinks
Provides-Extra: test
Requires-Dist: plone.app.testing; extra == "test"
Requires-Dist: collective.volto.blocksfield; extra == "test"
Requires-Dist: plone.testing>=5.0.0; extra == "test"
Requires-Dist: plone.app.contenttypes; extra == "test"
Requires-Dist: plone.app.robotframework[debug]; extra == "test"
Requires-Dist: collective.MockMailHost; extra == "test"
Dynamic: author
Dynamic: author-email
Dynamic: classifier
Dynamic: description
Dynamic: description-content-type
Dynamic: home-page
Dynamic: keywords
Dynamic: license
Dynamic: license-file
Dynamic: project-url
Dynamic: provides-extra
Dynamic: requires-dist
Dynamic: requires-python
Dynamic: summary
